{
  "id": "projects/vm-setup/overview",
  "title": "Virtual Machine Setup with Nginx and SSH Configuration",
  "description": "In this blog post, you’ll learn how to configure an existing virtual machine (VM) with nginx as a web server while also setting up a secure SSH configuration. We will walk through generating SSH keys, disabling password-based authentication, using SSH aliases, and managing multiple SSH identities.",
  "source": "@site/docs/projects/vm-setup/00-overview.md",
  "sourceDirName": "projects/vm-setup",
  "slug": "/projects/vm-setup/overview",
  "permalink": "/devsecops-blog/docs/projects/vm-setup/overview",
  "draft": false,
  "unlisted": false,
  "tags": [],
  "version": "current",
  "sidebarPosition": 0,
  "frontMatter": {},
  "sidebar": "tutorialSidebar",
  "previous": {
    "title": "Projects Intro",
    "permalink": "/devsecops-blog/docs/projects/intro"
  },
  "next": {
    "title": "Baby Tools Shop",
    "permalink": "/devsecops-blog/docs/projects/baby-tools-shop/overview"
  }
}